spectrumx/__init__.py
spectrumx/client.py
spectrumx/config.py
spectrumx/errors.py
spectrumx/gateway.py
spectrumx/utils.py
spectrumx/api/__init__.py
spectrumx/api/captures.py
spectrumx/api/datasets.py
spectrumx/api/sds_files.py
spectrumx/api/uploads.py
spectrumx/models/__init__.py
spectrumx/models/base.py
spectrumx/models/captures.py
spectrumx/models/datasets.py
spectrumx/models/files/__init__.py
spectrumx/models/files/file.py
spectrumx/models/files/permission.py
spectrumx/ops/.sds-ignore
spectrumx/ops/__init__.py
spectrumx/ops/files.py
spectrumx/ops/network.py
spectrumx/ops/pagination.py
spectrumx/vendor/__init__.py
spectrumx/vendor/xdg_base_dirs.py
spectrumx-0.1.17.dist-info/METADATA
spectrumx-0.1.17.dist-info/WHEEL
spectrumx-0.1.17.dist-info/RECORD
