Metadata-Version: 2.4
Name: spectrumx
Version: 0.1.17
Summary: SpectrumX Data System SDK
Project-URL: Changelog, https://github.com/spectrumx/sds-code/blob/master/sdk/docs/changelog.md
Project-URL: Documentation, https://github.com/spectrumx/sds-code/tree/master/sdk/docs
Project-URL: Issues, https://github.com/spectrumx/sds-code/issues
Project-URL: Repository, https://github.com/spectrumx/sds-code/tree/master/sdk
License-Expression: MIT
Classifier: Development Status :: 3 - Alpha
Classifier: Intended Audience :: Developers
Classifier: Intended Audience :: Science/Research
Classifier: License :: OSI Approved :: MIT License
Classifier: Operating System :: Unix
Classifier: Programming Language :: Python :: 3.11
Classifier: Programming Language :: Python :: 3.12
Classifier: Programming Language :: Python :: 3.13
Classifier: Programming Language :: Python :: 3.14
Classifier: Programming Language :: Python :: Implementation :: CPython
Classifier: Topic :: Scientific/Engineering :: Physics
Classifier: Topic :: Terminals
Classifier: Typing :: Typed
Requires-Python: >=3.11
Requires-Dist: blake3>=1.0.0; python_full_version < '3.14'
Requires-Dist: blake3>=1.0.6; python_full_version >= '3.14'
Requires-Dist: loguru>=0.6.0
Requires-Dist: pydantic>=2.11.0; python_full_version < '3.14'
Requires-Dist: pydantic>=2.12.0; python_full_version >= '3.14'
Requires-Dist: python-dotenv>=1.0.0
Requires-Dist: requests>=2.28.2
Requires-Dist: tqdm>=4.64.1
